lynara/__init__.py
lynara/py.typed
lynara/runner.py
lynara/types.py
lynara/interfaces/__init__.py
lynara/interfaces/api_http.py
lynara/interfaces/api_rest.py
lynara/interfaces/base.py
lynara/interfaces/lifespan.py
lynara/interfaces/utils.py
lynara-0.2.0.dist-info/METADATA
lynara-0.2.0.dist-info/WHEEL
lynara-0.2.0.dist-info/licenses/LICENSE
lynara-0.2.0.dist-info/RECORD
