Metadata-Version: 2.3
Name: lynara
Version: 0.2.0
Project-URL: Documentation, https://mirumee.github.io/lynara/
Project-URL: Issues, https://github.com/mirumee/lynara/issues
Project-URL: Source, https://github.com/mirumee/lynara
Author-email: Paweł Kucmus <pkucmus@gmail.com>
License-Expression: MIT
License-File: LICENSE
Classifier: Development Status :: 4 - Beta
Classifier: Programming Language :: Python
Classifier: Programming Language :: Python :: 3.10
Classifier: Programming Language :: Python :: 3.11
Classifier: Programming Language :: Python :: 3.12
Classifier: Programming Language :: Python :: Implementation :: CPython
Requires-Python: >=3.10
Provides-Extra: dev
Requires-Dist: ipdb; extra == 'dev'
Provides-Extra: docs
Requires-Dist: mkdocs-charts-plugin; extra == 'docs'
Requires-Dist: mkdocs-material; extra == 'docs'
Provides-Extra: types
Requires-Dist: django; extra == 'types'
Requires-Dist: django-stubs[compatible-mypy]; extra == 'types'
Requires-Dist: fastapi; extra == 'types'
Requires-Dist: mypy>=1.0.0; extra == 'types'
Requires-Dist: pytest; extra == 'types'
Requires-Dist: pytest-asyncio; extra == 'types'
